datacoin/__init__.py
datacoin/datacoin.py
pydatacoin-0.1.0.dist-info/LICENSE
pydatacoin-0.1.0.dist-info/METADATA
pydatacoin-0.1.0.dist-info/WHEEL
pydatacoin-0.1.0.dist-info/top_level.txt
pydatacoin-0.1.0.dist-info/RECORD
