Metadata-Version: 2.1
Name: pydatacoin
Version: 0.1.0
Summary: for working with blockchained files
Home-page: https://github.com/xloem/pydatacoin
Author: xloem
Author-email: 0xloem@gmail.com
License: UNKNOWN
Platform: UNKNOWN
Classifier: Programming Language :: Python :: 3
Classifier: Operating System :: OS Independent
Requires-Python: >=3.6
